ottoman_ner/__init__.py
ottoman_ner/cli.py
ottoman_ner/core.py
ottoman_ner/py.typed
ottoman_ner/utils/__init__.py
ottoman_ner/utils/logging_utils.py
ottoman_ner-2.0.0.dist-info/licenses/LICENSE
ottoman_ner-2.0.0.dist-info/METADATA
ottoman_ner-2.0.0.dist-info/WHEEL
ottoman_ner-2.0.0.dist-info/entry_points.txt
ottoman_ner-2.0.0.dist-info/top_level.txt
ottoman_ner-2.0.0.dist-info/RECORD
