Metadata-Version: 2.4
Name: ottoman-ner
Version: 2.0.0
Summary: Ottoman Turkish Named Entity Recognition toolkit
Home-page: https://github.com/fbkaragoz/ottoman-ner
Author: Fatih Burak Karagöz
Author-email: Fatih Burak Karagöz <fatihburak@pm.me>
Maintainer-email: Fatih Burak Karagöz <fatihburak@pm.me>
License: MIT
Project-URL: Homepage, https://github.com/fbkaragoz/ottoman-ner
Project-URL: Repository, https://github.com/fbkaragoz/ottoman-ner
Project-URL: Issues, https://github.com/fbkaragoz/ottoman-ner/issues
Project-URL: Documentation, https://github.com/fbkaragoz/ottoman-ner#readme
Keywords: nlp,ner,named-entity-recognition,ottoman-turkish,transformers,bert,historical-nlp
Classifier: Development Status :: 4 - Beta
Classifier: Intended Audience :: Developers
Classifier: Intended Audience :: Science/Research
Classifier: License :: OSI Approved :: MIT License
Classifier: Operating System :: OS Independent
Classifier: Programming Language :: Python :: 3
Classifier: Programming Language :: Python :: 3.8
Classifier: Programming Language :: Python :: 3.9
Classifier: Programming Language :: Python :: 3.10
Classifier: Programming Language :: Python :: 3.11
Classifier: Topic :: Scientific/Engineering :: Artificial Intelligence
Classifier: Topic :: Text Processing :: Linguistic
Requires-Python: >=3.8
License-File: LICENSE
Requires-Dist: torch>=1.9.0
Requires-Dist: transformers>=4.20.0
Requires-Dist: tokenizers>=0.12.0
Requires-Dist: datasets>=2.0.0
Requires-Dist: accelerate>=1.7.0
Requires-Dist: safetensors>=0.5.3
Requires-Dist: numpy>=1.21.0
Requires-Dist: pandas>=1.3.0
Requires-Dist: scikit-learn>=1.0.0
Requires-Dist: seqeval>=1.2.0
Requires-Dist: conllu>=4.5.3
Requires-Dist: PyYAML>=6.0
Requires-Dist: tqdm>=4.62.0
Provides-Extra: dev
Requires-Dist: pytest>=6.0.0; extra == "dev"
Requires-Dist: pytest-cov>=2.12.0; extra == "dev"
Requires-Dist: black>=21.0.0; extra == "dev"
Requires-Dist: isort>=5.9.0; extra == "dev"
Requires-Dist: flake8>=3.9.0; extra == "dev"
Requires-Dist: mypy>=0.910; extra == "dev"
Requires-Dist: pre-commit>=2.15.0; extra == "dev"
Provides-Extra: full
Requires-Dist: tensorboard>=2.8.0; extra == "full"
Requires-Dist: wandb>=0.12.0; extra == "full"
Requires-Dist: mlflow>=2.0.0; extra == "full"
Requires-Dist: matplotlib>=3.5.0; extra == "full"
Requires-Dist: seaborn>=0.11.0; extra == "full"
Dynamic: author
Dynamic: home-page
Dynamic: license-file
Dynamic: requires-python
